<annotation>
	<folder>greg</folder>
	<filename>6.2.jpg</filename>
	<path>C:\Users\Gregorie\Desktop\greg\6.2.jpg</path>
	<source>
		<database>Unknown</database>
	</source>
	<size>
		<width>4000</width>
		<height>3000</height>
		<depth>3</depth>
	</size>
	<segmented>0</segmented>
	<object>
		<name>6</name>
		<pose>Unspecified</pose>
		<truncated>0</truncated>
		<difficult>0</difficult>
		<bndbox>
			<xmin>360</xmin>
			<ymin>194</ymin>
			<xmax>851</xmax>
			<ymax>950</ymax>
		</bndbox>
	</object>
	<object>
		<name>6</name>
		<pose>Unspecified</pose>
		<truncated>0</truncated>
		<difficult>0</difficult>
		<bndbox>
			<xmin>1129</xmin>
			<ymin>228</ymin>
			<xmax>1466</xmax>
			<ymax>900</ymax>
		</bndbox>
	</object>
	<object>
		<name>6</name>
		<pose>Unspecified</pose>
		<truncated>0</truncated>
		<difficult>0</difficult>
		<bndbox>
			<xmin>1698</xmin>
			<ymin>356</ymin>
			<xmax>2013</xmax>
			<ymax>912</ymax>
		</bndbox>
	</object>
	<object>
		<name>6</name>
		<pose>Unspecified</pose>
		<truncated>0</truncated>
		<difficult>0</difficult>
		<bndbox>
			<xmin>2135</xmin>
			<ymin>337</ymin>
			<xmax>2432</xmax>
			<ymax>916</ymax>
		</bndbox>
	</object>
	<object>
		<name>6</name>
		<pose>Unspecified</pose>
		<truncated>0</truncated>
		<difficult>0</difficult>
		<bndbox>
			<xmin>2529</xmin>
			<ymin>334</ymin>
			<xmax>2804</xmax>
			<ymax>853</ymax>
		</bndbox>
	</object>
	<object>
		<name>6</name>
		<pose>Unspecified</pose>
		<truncated>0</truncated>
		<difficult>0</difficult>
		<bndbox>
			<xmin>473</xmin>
			<ymin>1059</ymin>
			<xmax>873</xmax>
			<ymax>1694</ymax>
		</bndbox>
	</object>
	<object>
		<name>6</name>
		<pose>Unspecified</pose>
		<truncated>0</truncated>
		<difficult>0</difficult>
		<bndbox>
			<xmin>1082</xmin>
			<ymin>969</ymin>
			<xmax>1460</xmax>
			<ymax>1544</ymax>
		</bndbox>
	</object>
	<object>
		<name>6</name>
		<pose>Unspecified</pose>
		<truncated>0</truncated>
		<difficult>0</difficult>
		<bndbox>
			<xmin>1641</xmin>
			<ymin>937</ymin>
			<xmax>1970</xmax>
			<ymax>1487</ymax>
		</bndbox>
	</object>
	<object>
		<name>6</name>
		<pose>Unspecified</pose>
		<truncated>0</truncated>
		<difficult>0</difficult>
		<bndbox>
			<xmin>2063</xmin>
			<ymin>944</ymin>
			<xmax>2348</xmax>
			<ymax>1428</ymax>
		</bndbox>
	</object>
	<object>
		<name>6</name>
		<pose>Unspecified</pose>
		<truncated>0</truncated>
		<difficult>0</difficult>
		<bndbox>
			<xmin>2441</xmin>
			<ymin>944</ymin>
			<xmax>2663</xmax>
			<ymax>1428</ymax>
		</bndbox>
	</object>
	<object>
		<name>6</name>
		<pose>Unspecified</pose>
		<truncated>0</truncated>
		<difficult>0</difficult>
		<bndbox>
			<xmin>604</xmin>
			<ymin>1844</ymin>
			<xmax>913</xmax>
			<ymax>2428</ymax>
		</bndbox>
	</object>
	<object>
		<name>6</name>
		<pose>Unspecified</pose>
		<truncated>0</truncated>
		<difficult>0</difficult>
		<bndbox>
			<xmin>1116</xmin>
			<ymin>1684</ymin>
			<xmax>1407</xmax>
			<ymax>2222</ymax>
		</bndbox>
	</object>
	<object>
		<name>6</name>
		<pose>Unspecified</pose>
		<truncated>0</truncated>
		<difficult>0</difficult>
		<bndbox>
			<xmin>1545</xmin>
			<ymin>1559</ymin>
			<xmax>1876</xmax>
			<ymax>2072</ymax>
		</bndbox>
	</object>
	<object>
		<name>6</name>
		<pose>Unspecified</pose>
		<truncated>0</truncated>
		<difficult>0</difficult>
		<bndbox>
			<xmin>2001</xmin>
			<ymin>1509</ymin>
			<xmax>2191</xmax>
			<ymax>1944</ymax>
		</bndbox>
	</object>
	<object>
		<name>6</name>
		<pose>Unspecified</pose>
		<truncated>0</truncated>
		<difficult>0</difficult>
		<bndbox>
			<xmin>2329</xmin>
			<ymin>1487</ymin>
			<xmax>2554</xmax>
			<ymax>1912</ymax>
		</bndbox>
	</object>
</annotation>
